[
  {
    "_id": "573c053d940a4faae163fc5d",
    "device": "xDrip-DexbridgeWixel",
    "date": 1463551291896,
    "dateString": "2016-05-18T07:01:31.896+0100",
    "sgv": 122,
    "direction": "Flat",
    "type": "sgv",
    "filtered": 140576,
    "unfiltered": 140032,
    "rssi": 100,
    "noise": 1,
    "sysTime": "2016-05-18T07:01:31.896+0100",
    "glucose": 122
  },
  {
    "_id": "573c0411940a4faae163fc50",
    "device": "xDrip-DexbridgeWixel",
    "date": 1463550991913,
    "dateString": "2016-05-18T06:56:31.913+0100",
    "sgv": 123,
    "direction": "Flat",
    "type": "sgv",
    "filtered": 139456,
    "unfiltered": 140384,
    "rssi": 100,
    "noise": 1,
    "sysTime": "2016-05-18T06:56:31.913+0100",
    "glucose": 123
  },
  {
    "_id": "573c02e5940a4faae163fc47",
    "device": "xDrip-DexbridgeWixel",
    "date": 1463550691742,
    "dateString": "2016-05-18T06:51:31.742+0100",
    "sgv": 124,
    "direction": "Flat",
    "type": "sgv",
    "filtered": 137952,
    "unfiltered": 141344,
    "rssi": 100,
    "noise": 1,
    "sysTime": "2016-05-18T06:51:31.742+0100",
    "glucose": 124
  },
  {
    "_id": "573c01ba940a4faae163fc40",
    "device": "xDrip-DexbridgeWixel",
    "date": 1463550391757,
    "dateString": "2016-05-18T06:46:31.757+0100",
    "sgv": 121,
    "direction": "Flat",
    "type": "sgv",
    "filtered": 136608,
    "unfiltered": 139072,
    "rssi": 100,
    "noise": 1,
    "sysTime": "2016-05-18T06:46:31.757+0100",
    "glucose": 121
  },
  {
    "_id": "573c008f940a4faae163fc37",
    "device": "xDrip-DexbridgeWixel",
    "date": 1463550091746,
    "dateString": "2016-05-18T06:41:31.746+0100",
    "sgv": 118,
    "direction": "Flat",
    "type": "sgv",
    "filtered": 135584,
    "unfiltered": 136608,
    "rssi": 100,
    "noise": 1,
    "sysTime": "2016-05-18T06:41:31.746+0100",
    "glucose": 118
  },
  {
    "_id": "573bff61940a4faae163fc2e",
    "device": "xDrip-DexbridgeWixel",
    "date": 1463549791925,
    "dateString": "2016-05-18T06:36:31.925+0100",
    "sgv": 117,
    "direction": "Flat",
    "type": "sgv",
    "filtered": 134848,
    "unfiltered": 136288,
    "rssi": 100,
    "noise": 1,
    "sysTime": "2016-05-18T06:36:31.925+0100",
    "glucose": 117
  },
  {
    "_id": "573bfe35940a4faae163fc23",
    "device": "xDrip-DexbridgeWixel",
    "date": 1463549491946,
    "dateString": "2016-05-18T06:31:31.946+0100",
    "sgv": 116,
    "direction": "Flat",
    "type": "sgv",
    "filtered": 134528,
    "unfiltered": 135616,
    "rssi": 100,
    "noise": 1,
    "sysTime": "2016-05-18T06:31:31.946+0100",
    "glucose": 116
  },
  {
    "_id": "573bfd09940a4faae163fc1b",
    "device": "xDrip-DexbridgeWixel",
    "date": 1463549191944,
    "dateString": "2016-05-18T06:26:31.944+0100",
    "sgv": 115,
    "direction": "Flat",
    "type": "sgv",
    "filtered": 134720,
    "unfiltered": 134656,
    "rssi": 100,
    "noise": 1,
    "sysTime": "2016-05-18T06:26:31.944+0100",
    "glucose": 115
  },
  {
    "_id": "573bfbde940a4faae163fc13",
    "device": "xDrip-DexbridgeWixel",
    "date": 1463548892968,
    "dateString": "2016-05-18T06:21:32.968+0100",
    "sgv": 115,
    "direction": "Flat",
    "type": "sgv",
    "filtered": 135136,
    "unfiltered": 134368,
    "rssi": 100,
    "noise": 1,
    "sysTime": "2016-05-18T06:21:32.968+0100",
    "glucose": 115
  },
  {
    "_id": "573bfab2940a4faae163fc0c",
    "device": "xDrip-DexbridgeWixel",
    "date": 1463548591941,
    "dateString": "2016-05-18T06:16:31.941+0100",
    "sgv": 115,
    "direction": "Flat",
    "type": "sgv",
    "filtered": 135264,
    "unfiltered": 134560,
    "rssi": 100,
    "noise": 1,
    "sysTime": "2016-05-18T06:16:31.941+0100",
    "glucose": 115
  }
]
